carskit_api/__init__.py
carskit_api/database.py
carskit_api/editors.py
carskit_api/managers.py
carskit_api/runner.py
carskit_api/carskit/CARSKit-v0.3.5.jar
carskit_api/carskit/debug.log
carskit_api/carskit/results.txt
carskit_api/carskit/results_all.txt
carskit_api/carskit/setting.conf
carskit_api/carskit/settings_data.json
carskit_api/cli/__init__.py
carskit_api/cli/database.py
carskit_api/cli/main.py
carskit_api/cli/message.py
carskit_api/cli/run.py
carskit_api/cli/settings.py
carskit_api/controllers/__init__.py
carskit_api/controllers/data_processing.py
carskit_api/controllers/mongo_connection.py
carskit_api/tests/__init__.py
carskit_api/tests/test_data_manager.py
carskit_api/tests/test_edit_settings.py
carskit_api/tests/test_run_carskit.py
carskit_api-0.0.7.dist-info/LICENSE.txt
carskit_api-0.0.7.dist-info/METADATA
carskit_api-0.0.7.dist-info/WHEEL
carskit_api-0.0.7.dist-info/entry_points.txt
carskit_api-0.0.7.dist-info/top_level.txt
carskit_api-0.0.7.dist-info/RECORD
