Metadata-Version: 2.1
Name: carskit-api
Version: 0.0.7
Summary: An API for the CARSKit engine
Home-page: UNKNOWN
Author: WagnoLeaoSergio
Author-email: wagnoleao@gmail.com
License: LICENSE.txt
Platform: UNKNOWN
Requires-Python: >=3.6
Requires-Dist: cliff
Requires-Dist: pickleDB
Requires-Dist: pymongo
Requires-Dist: dnspython
Requires-Dist: cryptography
